{
  "cookies": [
    {
      "name": "_gcl_au",
      "value": "1.1.1799053085.1755443180",
      "domain": ".baylor.edu",
      "path": "/",
      "expires": 1763219180,
      "httpOnly": false,
      "secure": false,
      "sameSite": "Lax"
    },
    {
      "name": "YSC",
      "value": "r3g1tNT544A",
      "domain": ".youtube.com",
      "path": "/",
      "expires": -1,
      "httpOnly": true,
      "secure": true,
      "sameSite": "None",
      "partitionKey": "https://baylor.edu",
      "_crHasCrossSiteAncestor": true
    },
    {
      "name": "VISITOR_INFO1_LIVE",
      "value": "MYANYHGpObA",
      "domain": ".youtube.com",
      "path": "/",
      "expires": 1771028065.198232,
      "httpOnly": true,
      "secure": true,
      "sameSite": "None",
      "partitionKey": "https://baylor.edu",
      "_crHasCrossSiteAncestor": true
    },
    {
      "name": "VISITOR_PRIVACY_METADATA",
      "value": "CgJVUxIEGgAgKQ%3D%3D",
      "domain": ".youtube.com",
      "path": "/",
      "expires": 1771028065.198255,
      "httpOnly": true,
      "secure": true,
      "sameSite": "None",
      "partitionKey": "https://baylor.edu",
      "_crHasCrossSiteAncestor": true
    },
    {
      "name": "_ga",
      "value": "GA1.1.1871101717.1755443180",
      "domain": ".baylor.edu",
      "path": "/",
      "expires": 1790069096.762316,
      "httpOnly": false,
      "secure": false,
      "sameSite": "Lax"
    },
    {
      "name": "__Secure-ROLLOUT_TOKEN",
      "value": "CLi3ueieq9KOOxC5hLO5j5KPAxiChr25j5KPAw%3D%3D",
      "domain": ".youtube.com",
      "path": "/",
      "expires": 1770995180.257944,
      "httpOnly": true,
      "secure": true,
      "sameSite": "None",
      "partitionKey": "https://baylor.edu",
      "_crHasCrossSiteAncestor": true
    },
    {
      "name": "_node",
      "value": "706d5032f60f7d5b4b441dc9fefb10df697c1164d8717d513b95a052a3031360",
      "domain": "apply.baylor.edu",
      "path": "/",
      "expires": -1,
      "httpOnly": false,
      "secure": true,
      "sameSite": "None"
    },
    {
      "name": "_hash",
      "value": "2461e5af-264f-4427-952e-ffb0cc23f325",
      "domain": "apply.baylor.edu",
      "path": "/",
      "expires": 1790003180.323835,
      "httpOnly": true,
      "secure": true,
      "sameSite": "None"
    },
    {
      "name": "_hashV",
      "value": "202508/1",
      "domain": "apply.baylor.edu",
      "path": "/",
      "expires": 1790003180.323862,
      "httpOnly": true,
      "secure": true,
      "sameSite": "None"
    },
    {
      "name": "_ttp",
      "value": "31Q4u0iZRBtxcx9RSECERHZjnzq",
      "domain": ".tiktok.com",
      "path": "/",
      "expires": 1789205096.876814,
      "httpOnly": false,
      "secure": true,
      "sameSite": "None"
    },
    {
      "name": "_tt_enable_cookie",
      "value": "1",
      "domain": ".baylor.edu",
      "path": "/",
      "expires": 1789205097,
      "httpOnly": false,
      "secure": false,
      "sameSite": "Lax"
    },
    {
      "name": "_ttp",
      "value": "01K2W92CZFAAMG735FAY4KZQYW_.tt.1",
      "domain": ".baylor.edu",
      "path": "/",
      "expires": 1789205097,
      "httpOnly": false,
      "secure": false,
      "sameSite": "Lax"
    },
    {
      "name": "_fbp",
      "value": "fb.1.1755443180550.227138050206019943",
      "domain": ".baylor.edu",
      "path": "/",
      "expires": 1763285097,
      "httpOnly": false,
      "secure": false,
      "sameSite": "Lax"
    },
    {
      "name": "receive-cookie-deprecation",
      "value": "1",
      "domain": ".doubleclick.net",
      "path": "/",
      "expires": 1771028068.016484,
      "httpOnly": true,
      "secure": true,
      "sameSite": "None",
      "partitionKey": "https://baylor.edu",
      "_crHasCrossSiteAncestor": true
    },
    {
      "name": "ssi",
      "value": "be12ca8f-f3a9-465b-a052-1bb87adb679d#1755443183340",
      "domain": ".sitescout.com",
      "path": "/",
      "expires": 1787045099.724873,
      "httpOnly": false,
      "secure": true,
      "sameSite": "None"
    },
    {
      "name": "inside-us",
      "value": "808735721-1540a857dd2821cd0983570682331850adea997268acc445d85ad11d005ab3c6-5-5",
      "domain": ".us-live.inside-graph.com",
      "path": "/",
      "expires": 1787045097.058394,
      "httpOnly": true,
      "secure": true,
      "sameSite": "None"
    },
    {
      "name": "VISITOR_INFO1_LIVE",
      "value": "MYANYHGpObA",
      "domain": ".youtube.com",
      "path": "/",
      "expires": 1771061096.520659,
      "httpOnly": true,
      "secure": true,
      "sameSite": "None"
    },
    {
      "name": "VISITOR_PRIVACY_METADATA",
      "value": "CgJVUxIEGgAgKQ%3D%3D",
      "domain": ".youtube.com",
      "path": "/",
      "expires": 1771061096.520685,
      "httpOnly": true,
      "secure": true,
      "sameSite": "None"
    },
    {
      "name": "_ga_576K0MV60P",
      "value": "GS2.1.s1755509096$o3$g0$t1755509096$j60$l0$h0",
      "domain": ".baylor.edu",
      "path": "/",
      "expires": 1790069096.718304,
      "httpOnly": false,
      "secure": false,
      "sameSite": "Lax"
    },
    {
      "name": "_ga_6WKDJN69W7",
      "value": "GS2.1.s1755509096$o3$g0$t1755509096$j60$l0$h0",
      "domain": ".baylor.edu",
      "path": "/",
      "expires": 1790069096.762137,
      "httpOnly": false,
      "secure": false,
      "sameSite": "Lax"
    },
    {
      "name": "ttcsid",
      "value": "1755509097057::bBxzXmfumn2gU2DxNsy4.3.1755509097057",
      "domain": ".baylor.edu",
      "path": "/",
      "expires": 1789205097,
      "httpOnly": false,
      "secure": false,
      "sameSite": "Lax"
    },
    {
      "name": "ttcsid_CKB048RC77UE2IQFCLB0",
      "value": "1755509097056::wiwCct2fQ_9SWsi99OYU.3.1755509097279",
      "domain": ".baylor.edu",
      "path": "/",
      "expires": 1789205097,
      "httpOnly": false,
      "secure": false,
      "sameSite": "Lax"
    },
    {
      "name": "NID",
      "value": "525=osES9Llc8J7mYVi8AFXQfnmizdpO19gTqftaCUWussZeOXRgqTtd7-8AxD5GWW9jtzYaRXt87WSshOEkPMIWaOW8PlA5rp8FWSn3sKkeraegH3Flm-3f2CHOWJQ2TVxfjB1WAJ3eC28RN1ph0rwxxL52bVq6CLdxA0Ah-9KutxGf7tauPN-AqofYsv2816EIO6LddQ",
      "domain": ".google.com",
      "path": "/",
      "expires": 1771254381.613178,
      "httpOnly": true,
      "secure": true,
      "sameSite": "None"
    },
    {
      "name": "test_cookie",
      "value": "CheckForPermission",
      "domain": ".doubleclick.net",
      "path": "/",
      "expires": 1755509997.67056,
      "httpOnly": true,
      "secure": true,
      "sameSite": "None"
    },
    {
      "name": "inside-us",
      "value": "808735721-1540a857dd2821cd0983570682331850adea997268acc445d85ad11d005ab3c6-0-0",
      "domain": ".baylor.edu",
      "path": "/",
      "expires": 1787045099,
      "httpOnly": false,
      "secure": true,
      "sameSite": "None"
    },
    {
      "name": "_ssuma",
      "value": "eyI0NSI6MTc1NTQ3NjA3MDY2NCwiNjgiOjE3NTU0NzYwNzA2NjQsIjI0IjoxNzU1NTA5MDk5NzMwLCI0OCI6MTc1NTUwOTA5OTczMCwiMzkiOjE3NTU1MDkwOTk3MzAsIjE3IjoxNzU1NDc2MDcwNjY0LCIyIjoxNzU1NDQzMTgzMzk0LCI0IjoxNzU1NDQzMTgzMzk0LCI3IjoxNzU1NDQzMTgzMzk0LCI4IjoxNzU1NDQzMTgzMzk0LCI1MyI6MTc1NTQ3NjA3MDY2NCwiNDIiOjE3NTU1MDkwOTk3MzAsIjEwIjoxNzU1NTA5MDk5NzMwfQ",
      "domain": ".sitescout.com",
      "path": "/",
      "expires": 1758101099.724926,
      "httpOnly": false,
      "secure": true,
      "sameSite": "None"
    }
  ],
  "origins": [
    {
      "origin": "https://admissions.web.baylor.edu",
      "localStorage": [
        {
          "name": "8763bb9c-0970-96f4-cca6-4c206c2a359d_st",
          "value": "1755509097627"
        },
        {
          "name": "lastExternalReferrer",
          "value": "empty"
        },
        {
          "name": "8763bb9c-0970-96f4-cca6-4c206c2a359d_pp",
          "value": "{}"
        },
        {
          "name": "_gcl_ls",
          "value": "{\"schema\":\"gcl\",\"version\":1,\"gcl_ctr\":{\"value\":{\"value\":0,\"creationTimeMs\":1755443179861},\"expires\":1763219179861}}"
        },
        {
          "name": "inside-us",
          "value": "808735721-1540a857dd2821cd0983570682331850adea997268acc445d85ad11d005ab3c6-5-5"
        },
        {
          "name": "lastExternalReferrerTime",
          "value": "1755509097064"
        },
        {
          "name": "topicsLastReferenceTime",
          "value": "1755509097634"
        }
      ]
    }
  ]
}