{
  "cookies": [
    {
      "name": "X-AB",
      "value": "12f715ca71194ad9a1b12bba6d1da4c6",
      "domain": "sc-static.net",
      "path": "/scevent.min.js",
      "expires": 1755654735.461368,
      "httpOnly": false,
      "secure": true,
      "sameSite": "None"
    },
    {
      "name": "_node",
      "value": "706d5032f60f7d5b4b441dc9fefb10df697c1164d8717d513b95a052a3031360",
      "domain": "gradadmissions.du.edu",
      "path": "/",
      "expires": -1,
      "httpOnly": false,
      "secure": true,
      "sameSite": "None"
    },
    {
      "name": "_hash",
      "value": "a4d18ae2-fb10-45f5-bb99-0109af49428f",
      "domain": "gradadmissions.du.edu",
      "path": "/",
      "expires": 1790013921.801703,
      "httpOnly": true,
      "secure": true,
      "sameSite": "None"
    },
    {
      "name": "_hashV",
      "value": "202508/1",
      "domain": "gradadmissions.du.edu",
      "path": "/",
      "expires": 1790013921.802933,
      "httpOnly": true,
      "secure": true,
      "sameSite": "None"
    },
    {
      "name": "_node",
      "value": "24cb4d6272b3a99e2195e26e8d714f3ce21a96f7c97ec09ea6f7c181d27bb3be",
      "domain": "admission.du.edu",
      "path": "/",
      "expires": -1,
      "httpOnly": false,
      "secure": true,
      "sameSite": "None"
    },
    {
      "name": "_hash",
      "value": "d19679e5-3a9f-48b8-bac5-3f00c7e8ec4e",
      "domain": "admission.du.edu",
      "path": "/",
      "expires": 1790013921.803496,
      "httpOnly": true,
      "secure": true,
      "sameSite": "None"
    },
    {
      "name": "_hashV",
      "value": "202508/1",
      "domain": "admission.du.edu",
      "path": "/",
      "expires": 1790013921.803523,
      "httpOnly": true,
      "secure": true,
      "sameSite": "None"
    },
    {
      "name": "csrf_token",
      "value": "3620a900-3134-4f8e-8861-79320da86a17",
      "domain": "www.du.edu",
      "path": "/",
      "expires": 1758045921,
      "httpOnly": false,
      "secure": true,
      "sameSite": "Lax",
      "partitionKey": "https://du.edu",
      "_crHasCrossSiteAncestor": false
    },
    {
      "name": "_gcl_au",
      "value": "1.1.1769219299.1755453922",
      "domain": ".du.edu",
      "path": "/",
      "expires": 1763229922,
      "httpOnly": false,
      "secure": false,
      "sameSite": "Lax"
    },
    {
      "name": "_rdt_uuid",
      "value": "1755453922869.86bc0021-9f57-479e-8652-baf9c0045973",
      "domain": ".du.edu",
      "path": "/",
      "expires": 1763229922,
      "httpOnly": false,
      "secure": true,
      "sameSite": "Strict"
    },
    {
      "name": "_attrb",
      "value": "%2285084441-f2ce-4973-bd66-63f55d3a5f33%22",
      "domain": ".du.edu",
      "path": "/",
      "expires": 1787104334,
      "httpOnly": false,
      "secure": false,
      "sameSite": "Lax"
    },
    {
      "name": "__pdst",
      "value": "dd848af9b7344b9d91d9d098287a6a3e",
      "domain": "www.du.edu",
      "path": "/",
      "expires": 1786989922,
      "httpOnly": false,
      "secure": false,
      "sameSite": "Strict"
    },
    {
      "name": "_ttp",
      "value": "31QQfx39XvIvXxcvc7UHv4asRdX",
      "domain": ".tiktok.com",
      "path": "/",
      "expires": 1789264335.565158,
      "httpOnly": false,
      "secure": true,
      "sameSite": "None"
    },
    {
      "name": "_fbp",
      "value": "fb.1.1755453923244.606978260433996283",
      "domain": ".du.edu",
      "path": "/",
      "expires": 1763344345,
      "httpOnly": false,
      "secure": false,
      "sameSite": "Lax"
    },
    {
      "name": "_tt_enable_cookie",
      "value": "1",
      "domain": ".du.edu",
      "path": "/",
      "expires": 1789264335,
      "httpOnly": false,
      "secure": false,
      "sameSite": "Lax"
    },
    {
      "name": "_ttp",
      "value": "01K2WKA812S3DCETVM2EVFYDCD_.tt.1",
      "domain": ".du.edu",
      "path": "/",
      "expires": 1789264335,
      "httpOnly": false,
      "secure": false,
      "sameSite": "Lax"
    },
    {
      "name": "sa-user-id",
      "value": "s%3A0-b404b12d-96e9-43e3-45ee-b4e629e34cda.lFsfcF6oZbSvSl6WXX9HMiCxxIfdvB3e7FerSiQeG9w",
      "domain": "qvdt3feo.com",
      "path": "/",
      "expires": 1786989923.396108,
      "httpOnly": false,
      "secure": true,
      "sameSite": "None"
    },
    {
      "name": "sa-user-id",
      "value": "s%3A0-b404b12d-96e9-43e3-45ee-b4e629e34cda.lFsfcF6oZbSvSl6WXX9HMiCxxIfdvB3e7FerSiQeG9w",
      "domain": ".qvdt3feo.com",
      "path": "/",
      "expires": 1786989923.396149,
      "httpOnly": false,
      "secure": true,
      "sameSite": "None"
    },
    {
      "name": "sa-user-id-v2",
      "value": "s%3AtASxLZbpQ-NF7rTmKeNM2g.5b1VqkkjjzuVffMRJ2dbQx%2FiK%2BwQ4PhKfAMWJxfr0ZU",
      "domain": "qvdt3feo.com",
      "path": "/",
      "expires": 1786989923.396164,
      "httpOnly": false,
      "secure": true,
      "sameSite": "None"
    },
    {
      "name": "sa-user-id-v2",
      "value": "s%3AtASxLZbpQ-NF7rTmKeNM2g.5b1VqkkjjzuVffMRJ2dbQx%2FiK%2BwQ4PhKfAMWJxfr0ZU",
      "domain": ".qvdt3feo.com",
      "path": "/",
      "expires": 1786989923.396173,
      "httpOnly": false,
      "secure": true,
      "sameSite": "None"
    },
    {
      "name": "sa-user-id-v3",
      "value": "s%3AAQAKIJTWOAh-X2chwPFDIxLSh5RwVoIds2BATugFdKBo5Z8GEL8CGAIg47OIxQY6BGFKycJCBDdj82I.371BIFqfdvSC70t3adDnkCd57oKgIdjqVGM1jH9SUQ0",
      "domain": "qvdt3feo.com",
      "path": "/",
      "expires": 1786989923.39618,
      "httpOnly": false,
      "secure": true,
      "sameSite": "None"
    },
    {
      "name": "sa-user-id-v3",
      "value": "s%3AAQAKIJTWOAh-X2chwPFDIxLSh5RwVoIds2BATugFdKBo5Z8GEL8CGAIg47OIxQY6BGFKycJCBDdj82I.371BIFqfdvSC70t3adDnkCd57oKgIdjqVGM1jH9SUQ0",
      "domain": ".qvdt3feo.com",
      "path": "/",
      "expires": 1786989923.396189,
      "httpOnly": false,
      "secure": true,
      "sameSite": "None"
    },
    {
      "name": "sa-user-id",
      "value": "s%253A0-b404b12d-96e9-43e3-45ee-b4e629e34cda.lFsfcF6oZbSvSl6WXX9HMiCxxIfdvB3e7FerSiQeG9w",
      "domain": "www.du.edu",
      "path": "/",
      "expires": 1786989923,
      "httpOnly": false,
      "secure": true,
      "sameSite": "Lax"
    },
    {
      "name": "sa-user-id-v2",
      "value": "s%253A.o6W7wkJsHSTU4%252BLlDruZ%252FwNjVcUZZMvakQpSatDoAgo",
      "domain": "www.du.edu",
      "path": "/",
      "expires": 1786989923,
      "httpOnly": false,
      "secure": true,
      "sameSite": "Lax"
    },
    {
      "name": "sa-user-id-v3",
      "value": "s%253AAQAKIJTWOAh-X2chwPFDIxLSh5RwVoIds2BATugFdKBo5Z8GEL8CGAIg47OIxQY6BGFKycJCBDdj82I.371BIFqfdvSC70t3adDnkCd57oKgIdjqVGM1jH9SUQ0",
      "domain": "www.du.edu",
      "path": "/",
      "expires": 1786989923,
      "httpOnly": false,
      "secure": true,
      "sameSite": "Lax"
    },
    {
      "name": "ttcsid_CUBVH1JC77U5QJJIA7R0",
      "value": "1755453923363::6qWajjQJDk9G8XuE73ZZ.1.1755453923607",
      "domain": ".du.edu",
      "path": "/",
      "expires": 1789149923,
      "httpOnly": false,
      "secure": false,
      "sameSite": "Lax"
    },
    {
      "name": "IDE",
      "value": "AHWqTUlNWDzSYAXO8wgpnBsVwzmpPDr2xlQ3J1--24yvoiELzJwIgEzaiFFBHXO1",
      "domain": ".doubleclick.net",
      "path": "/",
      "expires": 1790013924.922073,
      "httpOnly": true,
      "secure": true,
      "sameSite": "None"
    },
    {
      "name": "bcookie",
      "value": "\"v=2&0a8a3db2-e8d7-4982-8026-5a673455bc59\"",
      "domain": ".linkedin.com",
      "path": "/",
      "expires": 1787104336.918261,
      "httpOnly": false,
      "secure": true,
      "sameSite": "None"
    },
    {
      "name": "guid",
      "value": "bfcdd8b5-7b94-11f0-98fb-a3258a371a65",
      "domain": ".mountain.com",
      "path": "/",
      "expires": 1787104336.336866,
      "httpOnly": false,
      "secure": true,
      "sameSite": "None"
    },
    {
      "name": "tt",
      "value": "H4sIAAAAAAAAAKtWKlOyMqoFAP609q8HAAAA",
      "domain": ".px.mountain.com",
      "path": "/",
      "expires": 1786989926.350937,
      "httpOnly": false,
      "secure": true,
      "sameSite": "None"
    },
    {
      "name": "TDID",
      "value": "9ffca93b-57fd-4084-bb26-58ee94c8cba4",
      "domain": ".adsrvr.org",
      "path": "/",
      "expires": 1787104336.593946,
      "httpOnly": false,
      "secure": true,
      "sameSite": "None"
    },
    {
      "name": "audit_p",
      "value": "1|kzZZrSo0yd3pz8OYnBXuoA7eb22QS7/2sTtZkKg9BQKqcLSLiv9/T47sL2M+xx+cFDBlrBm3c6iM1KxoLazIt9i2Wk5FrGos0XY24Ec+XLu/yIgLbVA6xaK798n9KhFBO94/StOuRpwazLIoAMt1Rrc84N5/D1ZBONvkwZWUEatbOz6AjJtUa8ZnH3r7x5VAdeodiyl5GGjkt77VmXBK7kiCfUmSYXqD+ohH/uuQN8oOr/S07bYDcYQkZmofZQkSVSwKu1RXSJT0/fhu8/pkBO4VeIulq+4M1TRwmTZWV3Xc6UO785F0Pw==",
      "domain": ".rubiconproject.com",
      "path": "/",
      "expires": 1786989928.615927,
      "httpOnly": false,
      "secure": true,
      "sameSite": "None",
      "partitionKey": "https://du.edu",
      "_crHasCrossSiteAncestor": true
    },
    {
      "name": "khaos",
      "value": "MEFZY09Z-O-B9Q7",
      "domain": ".rubiconproject.com",
      "path": "/",
      "expires": 1786989928.61597,
      "httpOnly": false,
      "secure": true,
      "sameSite": "None"
    },
    {
      "name": "khaos_p",
      "value": "MEFZY09Z-O-B9Q7",
      "domain": ".rubiconproject.com",
      "path": "/",
      "expires": 1786989928.615981,
      "httpOnly": false,
      "secure": true,
      "sameSite": "None",
      "partitionKey": "https://du.edu",
      "_crHasCrossSiteAncestor": true
    },
    {
      "name": "audit",
      "value": "1|kzZZrSo0yd3pz8OYnBXuoA7eb22QS7/2sTtZkKg9BQKqcLSLiv9/T47sL2M+xx+cFDBlrBm3c6iM1KxoLazIt9i2Wk5FrGos0XY24Ec+XLu/yIgLbVA6xaK798n9KhFBO94/StOuRpwazLIoAMt1Rrc84N5/D1ZBONvkwZWUEatbOz6AjJtUa8ZnH3r7x5VAdeodiyl5GGjkt77VmXBK7kiCfUmSYXqD+ohH/uuQN8oOr/S07bYDcYQkZmofZQkSVSwKu1RXSJT0/fhu8/pkBO4VeIulq+4M1TRwmTZWV3Xc6UO785F0Pw==",
      "domain": ".rubiconproject.com",
      "path": "/",
      "expires": 1786989928.616,
      "httpOnly": false,
      "secure": true,
      "sameSite": "None"
    },
    {
      "name": "demdex",
      "value": "13040054341768491603772988349223250799",
      "domain": ".demdex.net",
      "path": "/",
      "expires": 1771005928.852814,
      "httpOnly": false,
      "secure": true,
      "sameSite": "None"
    },
    {
      "name": "dpm",
      "value": "13040054341768491603772988349223250799",
      "domain": ".dpm.demdex.net",
      "path": "/",
      "expires": 1771005928.852849,
      "httpOnly": false,
      "secure": true,
      "sameSite": "None"
    },
    {
      "name": "nitroCachedPage",
      "value": "0",
      "domain": "daniels.du.edu",
      "path": "/",
      "expires": -1,
      "httpOnly": false,
      "secure": false,
      "sameSite": "Lax"
    },
    {
      "name": "cmp649286385",
      "value": "f03623151eef3dd5744e29d11a934b50",
      "domain": "trackcmp.net",
      "path": "/",
      "expires": 1758246734.904625,
      "httpOnly": true,
      "secure": true,
      "sameSite": "None"
    },
    {
      "name": "csrf_token",
      "value": "7bf0e78d-3adc-4a68-b372-646b0c87ac1c",
      "domain": "daniels.du.edu",
      "path": "/",
      "expires": 1758045962,
      "httpOnly": false,
      "secure": true,
      "sameSite": "Lax",
      "partitionKey": "https://du.edu",
      "_crHasCrossSiteAncestor": false
    },
    {
      "name": "_scid",
      "value": "1ajPjc8vZzSNh0zVMuXIhai9iw2FkmKE",
      "domain": ".du.edu",
      "path": "/",
      "expires": 1789640660,
      "httpOnly": false,
      "secure": false,
      "sameSite": "Lax"
    },
    {
      "name": "__spdt",
      "value": "2f82d9fa54354c8eb39c37063fb04876",
      "domain": "daniels.du.edu",
      "path": "/",
      "expires": 1786989962,
      "httpOnly": false,
      "secure": false,
      "sameSite": "Strict"
    },
    {
      "name": "MR",
      "value": "0",
      "domain": ".bat.bing.com",
      "path": "/",
      "expires": 1756058762.618105,
      "httpOnly": false,
      "secure": true,
      "sameSite": "None"
    },
    {
      "name": "MUID",
      "value": "129E3763B1AF6DBD2E592128B0EB6CC3",
      "domain": ".bing.com",
      "path": "/",
      "expires": 1789149962.61798,
      "httpOnly": false,
      "secure": true,
      "sameSite": "None"
    },
    {
      "name": "_ScCbts",
      "value": "%5B%5D",
      "domain": ".du.edu",
      "path": "/",
      "expires": 1756058762,
      "httpOnly": false,
      "secure": false,
      "sameSite": "Lax"
    },
    {
      "name": "sc_at",
      "value": "v2|H4sIAAAAAAAAAE3GwRHAIAgEwIqYkRygSTfgDVVYvN/sa9mIXaulMpYY6pEMb2HSwHCdm0dtfDrdzfEGzq/jAp2/qHtAAAAA",
      "domain": ".snapchat.com",
      "path": "/",
      "expires": 1789149963.403802,
      "httpOnly": false,
      "secure": true,
      "sameSite": "None"
    },
    {
      "name": "TapAd_TS",
      "value": "1755453963255",
      "domain": ".tapad.com",
      "path": "/",
      "expires": 1760637964.621903,
      "httpOnly": false,
      "secure": true,
      "sameSite": "None"
    },
    {
      "name": "TapAd_DID",
      "value": "84f14f2c-2e1e-46fd-acc5-a5fca6472713",
      "domain": ".tapad.com",
      "path": "/",
      "expires": 1760637964.621922,
      "httpOnly": false,
      "secure": true,
      "sameSite": "None"
    },
    {
      "name": "_sctr",
      "value": "1%7C1755414000000",
      "domain": ".du.edu",
      "path": "/",
      "expires": 1789640661,
      "httpOnly": false,
      "secure": false,
      "sameSite": "Lax"
    },
    {
      "name": "CMID",
      "value": "aKIaDMAoI.YAL0U7AQcYogAA",
      "domain": ".casalemedia.com",
      "path": "/",
      "expires": 1787104336.43261,
      "httpOnly": false,
      "secure": true,
      "sameSite": "None"
    },
    {
      "name": "CMPS",
      "value": "2338",
      "domain": ".casalemedia.com",
      "path": "/",
      "expires": 1763229964.303243,
      "httpOnly": false,
      "secure": true,
      "sameSite": "None"
    },
    {
      "name": "CMPRO",
      "value": "2338",
      "domain": ".casalemedia.com",
      "path": "/",
      "expires": 1763344336.432641,
      "httpOnly": false,
      "secure": true,
      "sameSite": "None"
    },
    {
      "name": "IMRID",
      "value": "d72fb691-7b94-11f0-aefb-1112be5fae3c",
      "domain": ".imrworldwide.com",
      "path": "/",
      "expires": 1789149964.365109,
      "httpOnly": false,
      "secure": true,
      "sameSite": "None"
    },
    {
      "name": "uuid2",
      "value": "3388979792258981276",
      "domain": ".adnxs.com",
      "path": "/",
      "expires": 1763229964.468738,
      "httpOnly": true,
      "secure": true,
      "sameSite": "None"
    },
    {
      "name": "TapAd_3WAY_SYNCS",
      "value": "2!5514",
      "domain": ".tapad.com",
      "path": "/",
      "expires": 1760637964.621935,
      "httpOnly": false,
      "secure": true,
      "sameSite": "None"
    },
    {
      "name": "__cf_bm",
      "value": "ohZ3qsAPCCr4T3aLQVr7BpQB51SJH8j8oYvnt.dllDo-1755568334-1.0.1.1-zn1SaEUzyJLdpDxX_XQGvhfQdNr_qu8w4DgSOYEJ.Cx6dyWFLQjw85IStcIsuSe2df9ATfvTKY5KeXU_uVzdZdXlwS5Yc4Jm2zCZq60jTI0",
      "domain": ".nitroscripts.com",
      "path": "/",
      "expires": 1755570134.766367,
      "httpOnly": true,
      "secure": true,
      "sameSite": "None"
    },
    {
      "name": "_ga_MCHJZEGL1H",
      "value": "GS2.1.s1755568334$o2$g0$t1755568335$j59$l0$h0",
      "domain": ".du.edu",
      "path": "/",
      "expires": 1790128335.024394,
      "httpOnly": false,
      "secure": false,
      "sameSite": "Lax"
    },
    {
      "name": "_scid_r",
      "value": "3ijPjc8vZzSNh0zVMuXIhai9iw2FkmKE_d3VxA",
      "domain": ".du.edu",
      "path": "/",
      "expires": 1789755033,
      "httpOnly": false,
      "secure": false,
      "sameSite": "Lax"
    },
    {
      "name": "_ga_KRF5TZRR3S",
      "value": "GS2.1.s1755568335$o2$g0$t1755568335$j60$l0$h0",
      "domain": ".du.edu",
      "path": "/",
      "expires": 1790128335.528244,
      "httpOnly": false,
      "secure": false,
      "sameSite": "Lax"
    },
    {
      "name": "CLID",
      "value": "7a150e0b7ed2477f8db47893428fcf65.20250817.20260819",
      "domain": "www.clarity.ms",
      "path": "/",
      "expires": 1787104335.545328,
      "httpOnly": true,
      "secure": true,
      "sameSite": "None"
    },
    {
      "name": "_uetsid",
      "value": "21bf64f07c9f11f0905ec5dbf3917149",
      "domain": ".du.edu",
      "path": "/",
      "expires": 1755654735,
      "httpOnly": false,
      "secure": false,
      "sameSite": "Lax"
    },
    {
      "name": "_uetvid",
      "value": "bea755907b9411f0b24a85dbb7dc7d68",
      "domain": ".du.edu",
      "path": "/",
      "expires": 1789264335,
      "httpOnly": false,
      "secure": false,
      "sameSite": "Lax"
    },
    {
      "name": "ttcsid",
      "value": "1755568335827::7P77GnRJ62_g4x-5L67s.2.1755568335827",
      "domain": ".du.edu",
      "path": "/",
      "expires": 1789264335,
      "httpOnly": false,
      "secure": false,
      "sameSite": "Lax"
    },
    {
      "name": "_clck",
      "value": "qw0cqu%7C2%7Cfyl%7C0%7C2055",
      "domain": ".du.edu",
      "path": "/",
      "expires": 1787104335,
      "httpOnly": false,
      "secure": false,
      "sameSite": "Lax"
    },
    {
      "name": "lidc",
      "value": "\"b=TGST09:s=T:r=T:a=T:p=T:g=3101:u=1:x=1:i=1755568336:t=1755654736:v=2:sig=AQEEJzZl88rMPqPy_l57-lKZX21V12as\"",
      "domain": ".linkedin.com",
      "path": "/",
      "expires": 1755654736.918362,
      "httpOnly": false,
      "secure": true,
      "sameSite": "None"
    },
    {
      "name": "ar_debug",
      "value": "1",
      "domain": "px.ads.linkedin.com",
      "path": "/",
      "expires": 1758198081.918159,
      "httpOnly": true,
      "secure": true,
      "sameSite": "None"
    },
    {
      "name": "_ga_CMGRJVENZ2",
      "value": "GS2.1.s1755568335$o2$g0$t1755568336$j59$l0$h0",
      "domain": ".du.edu",
      "path": "/",
      "expires": 1790128336.048092,
      "httpOnly": false,
      "secure": false,
      "sameSite": "Lax"
    },
    {
      "name": "_ga",
      "value": "GA1.2.1190091860.1755453923",
      "domain": ".du.edu",
      "path": "/",
      "expires": 1790128336.195503,
      "httpOnly": false,
      "secure": false,
      "sameSite": "Lax"
    },
    {
      "name": "_gid",
      "value": "GA1.2.73149018.1755568336",
      "domain": ".du.edu",
      "path": "/",
      "expires": 1755654736,
      "httpOnly": false,
      "secure": false,
      "sameSite": "Lax"
    },
    {
      "name": "_gat_UA-50286807-5",
      "value": "1",
      "domain": ".du.edu",
      "path": "/",
      "expires": 1755568396,
      "httpOnly": false,
      "secure": false,
      "sameSite": "Lax"
    },
    {
      "name": "__cf_bm",
      "value": "aOwGDAg0lMCvFXnX4_HQ3MYw9Z4.7Xn_iuv98du8Hic-1755568336-1.0.1.1-0wwJLxr0f9eSC1bKkVJigWQ9R81CXSAsqv2_zokpmXCYR29TmQM.I1pQO6_P32AM.sgLt46PnuMoEbXyuHgvoN5yVARrlAT2AVeqw7OaUTg",
      "domain": ".getnitropack.com",
      "path": "/",
      "expires": 1755570136.364901,
      "httpOnly": true,
      "secure": true,
      "sameSite": "None"
    },
    {
      "name": "ab",
      "value": "0001%3AponWIHNSfe9gyHi9R1V8x21kwM%2BTjs5%2F",
      "domain": ".agkn.com",
      "path": "/",
      "expires": 1787104336.563957,
      "httpOnly": false,
      "secure": true,
      "sameSite": "None"
    },
    {
      "name": "clid",
      "value": "2t17x74011702tg00aw08go8000000016e010y01801",
      "domain": ".media6degrees.com",
      "path": "/",
      "expires": 1771120336.542708,
      "httpOnly": false,
      "secure": true,
      "sameSite": "None"
    },
    {
      "name": "acs",
      "value": "012020k1t17x74xzt10",
      "domain": ".media6degrees.com",
      "path": "/",
      "expires": 1771120336.542757,
      "httpOnly": false,
      "secure": true,
      "sameSite": "None"
    },
    {
      "name": "u",
      "value": "C|0AAAAAAAAMDaVUAAAAAAA",
      "domain": ".agkn.com",
      "path": "/",
      "expires": 1787104336.563967,
      "httpOnly": false,
      "secure": true,
      "sameSite": "None"
    },
    {
      "name": "TDCPM",
      "value": "CAESEgoDYWFtEgsIiLeW39Xwrj4QBRIWCgdydWJpY29uEgsI0NuW39Xwrj4QBRIVCgZnb29nbGUSCwj4_pbf1fCuPhAFEhcKCGFwcG5leHVzEgsIotvwu9jwrj4QBRIUCgV0YXBhZBILCMK96rXY8K4-EAUSFgoHbGh3Yms1ORILCMLj6rXY8K4-EAUSFgoHYWRkdGhpcxILCPTC3eqhs68-EAUSGAoJYWRhZHZpc29yEgsIwO7d6qGzrz4QBRIVCgZjYXNhbGUSCwjgmt7qobOvPhAFGAUgASgGMgsImojgl7izrz4QBTgBQgQiAggBWgc3a3doazllYAE.",
      "domain": ".adsrvr.org",
      "path": "/",
      "expires": 1787104336.593988,
      "httpOnly": false,
      "secure": true,
      "sameSite": "None"
    },
    {
      "name": "ttcsid_CEHKQ1JC77U4LISTUKFG",
      "value": "1755568335826::HASmtrjDXmYLrSZoDwCX.2.1755568345405",
      "domain": ".du.edu",
      "path": "/",
      "expires": 1789264345,
      "httpOnly": false,
      "secure": false,
      "sameSite": "Lax"
    }
  ],
  "origins": [
    {
      "origin": "https://daniels.du.edu",
      "localStorage": [
        {
          "name": "u_sclid",
          "value": "pP3sGfoP70eYnpJYAMxmSpEBqJmwcuqX1ajPjc8vZzSNh0zVMuXIhai9iw2FkmKE"
        },
        {
          "name": "_uetvid_exp",
          "value": "Sun, 13 Sep 2026 01:52:15 GMT"
        },
        {
          "name": "_attrb",
          "value": "\"85084441-f2ce-4973-bd66-63f55d3a5f33\""
        },
        {
          "name": "_gcl_ls",
          "value": "{\"schema\":\"gcl\",\"version\":1,\"gcl_ctr\":{\"value\":{\"value\":0,\"creationTimeMs\":1755453961915},\"expires\":1763229961915}}"
        },
        {
          "name": "attr_group_properties",
          "value": "{}"
        },
        {
          "name": "_attrg",
          "value": "null"
        },
        {
          "name": "attr_user_traits",
          "value": "{}"
        },
        {
          "name": "_attru",
          "value": "null"
        },
        {
          "name": "_uetvid",
          "value": "bea755907b9411f0b24a85dbb7dc7d68"
        },
        {
          "name": "lastExternalReferrer",
          "value": "empty"
        },
        {
          "name": "li_adsId",
          "value": "c3d58ce1-af01-4100-bc9f-823e777e6b08"
        },
        {
          "name": "Attribution.a0bed92b-73f2-4730-9108-a2191c11d151.queue",
          "value": "[]"
        },
        {
          "name": "7d260db6-4368-c774-b952-797964417b99_st",
          "value": "1755568335284"
        },
        {
          "name": "topicsLastReferenceTime",
          "value": "1755568345393"
        },
        {
          "name": "7d260db6-4368-c774-b952-797964417b99_pp",
          "value": "{}"
        },
        {
          "name": "lo_session",
          "value": "{\"__s\":1755453962856}"
        },
        {
          "name": "Attribution.a0bed92b-73f2-4730-9108-a2191c11d151.reclaimEnd",
          "value": "null"
        },
        {
          "name": "_uetsid",
          "value": "21bf64f07c9f11f0905ec5dbf3917149"
        },
        {
          "name": "TERMLY_API_CACHE",
          "value": "{\"TERMLY_STATISTIC\":{\"createdAt\":1755453962315,\"value\":\"__tltpl_af6a0a0d-7408-4229-aa83-dfd7585f9071\"},\"__tltpl_af6a0a0d-7408-4229-aa83-dfd7585f9071\":{\"createdAt\":1755568335074,\"value\":{\"cf220ee8-53af-4eda-9b67-a9ab07e17f96\":{\"notify\":true,\"version\":20,\"showBanner\":true}}}}"
        },
        {
          "name": "u_sclid_r",
          "value": "vX3sGfoP70eYnpJYAMxmSpEBqJmwcuqXy7Rzid4oz43PL2c0jYdM1TLlyIWovYsNhZJihP3d1cQ"
        },
        {
          "name": "Attribution.a0bed92b-73f2-4730-9108-a2191c11d151.inProgress",
          "value": "{}"
        },
        {
          "name": "lastExternalReferrerTime",
          "value": "1755568335758"
        },
        {
          "name": "_uetsid_exp",
          "value": "Wed, 20 Aug 2025 01:52:15 GMT"
        },
        {
          "name": "Attribution.a0bed92b-73f2-4730-9108-a2191c11d151.reclaimStart",
          "value": "null"
        },
        {
          "name": "Attribution.a0bed92b-73f2-4730-9108-a2191c11d151.ack",
          "value": "1755568346851"
        },
        {
          "name": "debug",
          "value": "undefined"
        },
        {
          "name": "termly_gtm_template_default_consents",
          "value": "{\"ad_personalization\":\"granted\",\"ad_storage\":\"granted\",\"ad_user_data\":\"granted\",\"analytics_storage\":\"granted\",\"functionality_storage\":\"granted\",\"personalization_storage\":\"granted\",\"security_storage\":\"granted\",\"social_storage\":\"granted\",\"unclassified_storage\":\"granted\"}"
        }
      ]
    },
    {
      "origin": "https://www.du.edu",
      "localStorage": [
        {
          "name": "sa-user-id",
          "value": "s%3A0-b404b12d-96e9-43e3-45ee-b4e629e34cda.lFsfcF6oZbSvSl6WXX9HMiCxxIfdvB3e7FerSiQeG9w"
        },
        {
          "name": "Attribution.f26af9be-cc4f-40c5-8259-a72bd77da7ff.reclaimStart",
          "value": "null"
        },
        {
          "name": "NRBA_SESSION",
          "value": "{\"value\":\"27df5d72facc1507\",\"inactiveAt\":1755455745770,\"expiresAt\":1755468327819,\"updatedAt\":1755453945770,\"sessionReplayMode\":0,\"sessionReplaySentFirstChunk\":false,\"sessionTraceMode\":0,\"traceHarvestStarted\":false,\"loggingMode\":0,\"serverTimeDiff\":-183,\"custom\":{},\"numOfResets\":0}"
        },
        {
          "name": "_uetvid_exp",
          "value": "Fri, 11 Sep 2026 18:05:23 GMT"
        },
        {
          "name": "topicsLastReferenceTime",
          "value": "1755453924999"
        },
        {
          "name": "7d260db6-4368-c774-b952-797964417b99_pp",
          "value": "{}"
        },
        {
          "name": "a63d66b1-4d1d-acd9-9069-948877840f27_pp",
          "value": "{}"
        },
        {
          "name": "a63d66b1-4d1d-acd9-9069-948877840f27_st",
          "value": "1755453922006"
        },
        {
          "name": "Attribution.f26af9be-cc4f-40c5-8259-a72bd77da7ff.inProgress",
          "value": "{}"
        },
        {
          "name": "Attribution.f26af9be-cc4f-40c5-8259-a72bd77da7ff.reclaimEnd",
          "value": "null"
        },
        {
          "name": "_attrb",
          "value": "\"85084441-f2ce-4973-bd66-63f55d3a5f33\""
        },
        {
          "name": "_gcl_ls",
          "value": "{\"schema\":\"gcl\",\"version\":1,\"gcl_ctr\":{\"value\":{\"value\":1,\"creationTimeMs\":1755453923428},\"expires\":1763229923428}}"
        },
        {
          "name": "_uetsid",
          "value": "bea729007b9411f0b30ad12fdea129ad"
        },
        {
          "name": "sa-user-id-v3",
          "value": "s%3AAQAKIJTWOAh-X2chwPFDIxLSh5RwVoIds2BATugFdKBo5Z8GEL8CGAIg47OIxQY6BGFKycJCBDdj82I.371BIFqfdvSC70t3adDnkCd57oKgIdjqVGM1jH9SUQ0"
        },
        {
          "name": "sa-user-id-v2",
          "value": "s%3A.o6W7wkJsHSTU4%2BLlDruZ%2FwNjVcUZZMvakQpSatDoAgo"
        },
        {
          "name": "Attribution.f26af9be-cc4f-40c5-8259-a72bd77da7ff.ack",
          "value": "1755453931904"
        },
        {
          "name": "TERMLY_API_CACHE",
          "value": "{\"TERMLY_STATISTIC\":{\"createdAt\":1755453921777,\"value\":\"__tltpl_7ba1b5fc-00c7-40fb-b9cb-ebbd46725653\"},\"__tltpl_7ba1b5fc-00c7-40fb-b9cb-ebbd46725653\":{\"createdAt\":1755453944497,\"value\":{\"6decb663-9355-4356-8bf5-17619f343e54\":{\"notify\":true,\"version\":18,\"showBanner\":true}}},\"__tltpl_3360257\":{\"createdAt\":1755453945771,\"value\":{\"6decb663-9355-4356-8bf5-17619f343e54\":{\"notify\":true,\"version\":18,\"showBanner\":false}}},\"__tluid\":{\"createdAt\":1755453947537,\"value\":\"fe3c6701-20ad-4d52-90e5-c26a89529315\"},\"TERMLY_COOKIE_CONSENT\":{\"createdAt\":1755453947537,\"value\":{\"performance\":true,\"analytics\":true,\"advertising\":true,\"social_networking\":true,\"unclassified\":true,\"essential\":true,\"ac_string\":null,\"document_version_id\":21187636,\"event_type\":\"banner\",\"gpc\":false,\"id\":1755453947576,\"tc_string\":null,\"template_version_id\":21187636,\"visitor\":{\"uuid\":\"fe3c6701-20ad-4d52-90e5-c26a89529315\"},\"visitor_id\":\"fe3c6701-20ad-4d52-90e5-c26a89529315\"}}}"
        },
        {
          "name": "Attribution.f26af9be-cc4f-40c5-8259-a72bd77da7ff.queue",
          "value": "[]"
        },
        {
          "name": "attr_group_properties",
          "value": "{}"
        },
        {
          "name": "lastExternalReferrerTime",
          "value": "1755453923241"
        },
        {
          "name": "_attrg",
          "value": "null"
        },
        {
          "name": "_uetsid_exp",
          "value": "Mon, 18 Aug 2025 18:05:23 GMT"
        },
        {
          "name": "attr_user_traits",
          "value": "{}"
        },
        {
          "name": "_attru",
          "value": "null"
        },
        {
          "name": "_uetvid",
          "value": "bea755907b9411f0b24a85dbb7dc7d68"
        },
        {
          "name": "lastExternalReferrer",
          "value": "empty"
        },
        {
          "name": "li_adsId",
          "value": "fbac769b-b4db-4d5c-b533-2ed51ce7abbf"
        },
        {
          "name": "debug",
          "value": "undefined"
        },
        {
          "name": "7d260db6-4368-c774-b952-797964417b99_st",
          "value": "1755453921998"
        }
      ]
    }
  ]
}