{
  "cookies": [
    {
      "name": "_ga",
      "value": "GA1.1.1660828768.1755433835",
      "domain": ".upenn.edu",
      "path": "/",
      "expires": 1789993835,
      "httpOnly": false,
      "secure": false,
      "sameSite": "Lax"
    },
    {
      "name": "_ga_Y5TMFZNHBR",
      "value": "GS2.1.s1755433835$o1$g0$t1755433835$j60$l0$h0",
      "domain": ".upenn.edu",
      "path": "/",
      "expires": 1789993835,
      "httpOnly": false,
      "secure": false,
      "sameSite": "Lax"
    },
    {
      "name": "__cf_bm",
      "value": "QDLvvKNhC59sOu8OvdUduv4K9phV1ZiTeqiur5owyc4-1775190031.1339061-1.0.1.1-qk552zJL4Pl2m7pvSCTwvRrcq.qZ1z0FPtl8RhJY3x0MjQDUZrjizfPMBSzR6yk_U81taNJDqQownYOexwjkKyV8QWcjXyAy4g_5j474G.B.98aMn7JDFFJXMZkklN0Y",
      "domain": ".vimeo.com",
      "path": "/",
      "expires": 1775191831,
      "httpOnly": true,
      "secure": true,
      "sameSite": "None"
    },
    {
      "name": "_cfuvid",
      "value": "_MQhUlOHR6Y6pgi8qPXet.j.XdRPFUqCVpcKCm5iXTM-1775190031.1339061-1.0.1.1-lRTUSGqkWKXaDlN3PSyOWvcA4Pd5u_t28H4.5KJ6xFI",
      "domain": ".vimeo.com",
      "path": "/",
      "expires": -1,
      "httpOnly": true,
      "secure": true,
      "sameSite": "None"
    },
    {
      "name": "vuid",
      "value": "pl1619974007.205410113",
      "domain": ".vimeo.com",
      "path": "/",
      "expires": 1809750032,
      "httpOnly": false,
      "secure": true,
      "sameSite": "None"
    }
  ],
  "origins": [
    {
      "origin": "https://player.vimeo.com",
      "localStorage": [
        {
          "name": "LOCAL_STORAGE_ID_VIMEO_PLAYER",
          "value": "fc994d7f-73ea-458b-8003-234d97e7e254"
        },
        {
          "name": "LOCAL_STORAGE_ID_PICOX_ID",
          "value": "a978770f-fd8a-4d53-b075-d0805f121627"
        }
      ]
    }
  ]
}