{
  "cookies": [
    {
      "name": "__cf_bm",
      "value": "cfX1F.0WB1aQ5yy0XzcCAnR._KPSHT6TVasa2JU.5NU-1755440035-1.0.1.1-cCkmG687AFVbThkb4sErBrYBhrmN0TvTAI8idi.uONF0faxlDryBlXtYCKUPFhdORn5OcmC.NIIylG8YmCt7Hvx3Ds9IGdpSTQLURjmAyrQ",
      "domain": ".nsfp.unc.edu",
      "path": "/",
      "expires": 1755441835.14086,
      "httpOnly": true,
      "secure": true,
      "sameSite": "None"
    },
    {
      "name": "_ga_HNF2L3S2SM",
      "value": "GS2.1.s1755440036$o1$g0$t1755440036$j60$l0$h0",
      "domain": ".unc.edu",
      "path": "/",
      "expires": 1790000036.003618,
      "httpOnly": false,
      "secure": false,
      "sameSite": "Lax"
    },
    {
      "name": "_ga",
      "value": "GA1.1.1317793145.1755440036",
      "domain": ".unc.edu",
      "path": "/",
      "expires": 1790000036.003755,
      "httpOnly": false,
      "secure": false,
      "sameSite": "Lax"
    }
  ],
  "origins": [
    {
      "origin": "https://nsfp.unc.edu",
      "localStorage": [
        {
          "name": "brx_popup_3174_lastShown",
          "value": "1755440035839"
        },
        {
          "name": "verified",
          "value": "verified"
        }
      ]
    }
  ]
}