{
  "cookies": [
    {
      "name": "_ga_RJSVG73M20",
      "value": "GS2.1.s1775130363$o1$g0$t1775130363$j60$l0$h0",
      "domain": ".virginia.edu",
      "path": "/",
      "expires": 1809690363,
      "httpOnly": false,
      "secure": false,
      "sameSite": "None"
    },
    {
      "name": "_ga",
      "value": "GA1.1.391366595.1775130364",
      "domain": ".virginia.edu",
      "path": "/",
      "expires": 1809690363,
      "httpOnly": false,
      "secure": false,
      "sameSite": "None"
    },
    {
      "name": "_ga_FDKRQXBHCW",
      "value": "GS2.1.s1775130363$o1$g0$t1775130363$j60$l0$h0",
      "domain": ".virginia.edu",
      "path": "/",
      "expires": 1809690363,
      "httpOnly": false,
      "secure": false,
      "sameSite": "None"
    },
    {
      "name": "_ga_K247NQMNHY",
      "value": "GS2.1.s1775130363$o1$g0$t1775130363$j60$l0$h0",
      "domain": ".virginia.edu",
      "path": "/",
      "expires": 1809690363,
      "httpOnly": false,
      "secure": false,
      "sameSite": "None"
    },
    {
      "name": "_ga_Q0SPMKD7KK",
      "value": "GS2.1.s1775130363$o1$g0$t1775130363$j60$l0$h0",
      "domain": ".virginia.edu",
      "path": "/",
      "expires": 1809690363,
      "httpOnly": false,
      "secure": false,
      "sameSite": "None"
    },
    {
      "name": "cf_clearance",
      "value": "ObeEQTOjqn5eKegaSqbUxnpdXvuIMLi3O8Z.oFVMfqw-1775130364-1.2.1.1-Upgurx_a87DAOdd3kewRQ2ucdLnw3tE0EwQj7w1QVzDZDvqQI8WDYZzpmdmzUwLHKp3LVWxCgSB_8CYFly8mcvdroVhltxpOY9_hJs59UT3p.YRVNLmUoecJtNJQQc5QkegWuX6HqLdTbY4xMj24yEnGLNlfJkAGTC27ZtBn72Ro.PBRANTvIhP9z5nlWiav5w991eRo_G0fDFKfTMx.tUBr_AiyK7v2ZsrAakR8H2M",
      "domain": ".virginia.edu",
      "path": "/",
      "expires": 1806666364,
      "httpOnly": true,
      "secure": true,
      "sameSite": "None"
    },
    {
      "name": "__cf_bm",
      "value": "kbpM70kCxrtRZIq0Yc_LY9U0wSAgVlx8hXozRYqQlFI-1775130364.6137288-1.0.1.1-zG9sX030Y2noeSb9jXyMU3IWiRoafJgdgH2IPKfgG9CxsZxkBTovOrhgYGBYLS8vzzfLU13u_n45KlJBV4ANJ5ZFss.rzsfi3dpXKxNOLZT4u9zR3m9ZJRizO1kEKyEG",
      "domain": ".virginia.edu",
      "path": "/",
      "expires": 1775132164,
      "httpOnly": true,
      "secure": true,
      "sameSite": "None"
    },
    {
      "name": "YSC",
      "value": "XQIqTz-qdmY",
      "domain": ".youtube.com",
      "path": "/",
      "expires": -1,
      "httpOnly": true,
      "secure": true,
      "sameSite": "None"
    },
    {
      "name": "VISITOR_INFO1_LIVE",
      "value": "AxfkdRZuRwA",
      "domain": ".youtube.com",
      "path": "/",
      "expires": 1790682682,
      "httpOnly": true,
      "secure": true,
      "sameSite": "None"
    },
    {
      "name": "VISITOR_PRIVACY_METADATA",
      "value": "CgJVUxIEGgAgSA%3D%3D",
      "domain": ".youtube.com",
      "path": "/",
      "expires": 1790682682,
      "httpOnly": true,
      "secure": true,
      "sameSite": "None"
    },
    {
      "name": "__Secure-ROLLOUT_TOKEN",
      "value": "CLbSh9_ojYz4QxD4vuuNjc-TAxj4vuuNjc-TAw%3D%3D",
      "domain": ".youtube.com",
      "path": "/",
      "expires": 1790682682,
      "httpOnly": true,
      "secure": true,
      "sameSite": "None"
    }
  ],
  "origins": [
    {
      "origin": "https://www.youtube.com",
      "localStorage": [
        {
          "name": "yt-icons-last-purged",
          "value": "1770295882740"
        },
        {
          "name": "ytidb::LAST_RESULT_ENTRY_KEY",
          "value": "{\"data\":{\"hasSucceededOnce\":true},\"expiration\":1777722685963,\"creation\":1775130685963}"
        }
      ]
    }
  ]
}