{
  "cookies": [
    {
      "name": "X-AB",
      "value": "12f715ca71194ad9a1b12bba6d1da4c6",
      "domain": "sc-static.net",
      "path": "/scevent.min.js",
      "expires": 1755541298.827705,
      "httpOnly": false,
      "secure": true,
      "sameSite": "None"
    },
    {
      "name": "BCSessionID",
      "value": "e8036c00-d824-4e26-b6f3-0458bfb5053c",
      "domain": "v285.clarkson.edu",
      "path": "/DG/DEFAULT",
      "expires": 1790084825.587142,
      "httpOnly": false,
      "secure": true,
      "sameSite": "None"
    },
    {
      "name": "BCSessionID",
      "value": "e8036c00-d824-4e26-b6f3-0458bfb5053c",
      "domain": "clarkson.blueconic.net",
      "path": "/DG/DEFAULT",
      "expires": 1787027729.800552,
      "httpOnly": true,
      "secure": true,
      "sameSite": "None"
    },
    {
      "name": "_node",
      "value": "0884b6b69328a2f83a877fac94eb03198b4762757c0dcd5c7c1d88badc29cb79",
      "domain": "undergrad.clarkson.edu",
      "path": "/",
      "expires": -1,
      "httpOnly": false,
      "secure": true,
      "sameSite": "None"
    },
    {
      "name": "_hash",
      "value": "b020d22f-2610-490f-ad08-511d112e52ac",
      "domain": "undergrad.clarkson.edu",
      "path": "/",
      "expires": 1790014894.824899,
      "httpOnly": true,
      "secure": true,
      "sameSite": "None"
    },
    {
      "name": "_hashV",
      "value": "202508/1",
      "domain": "undergrad.clarkson.edu",
      "path": "/",
      "expires": 1790014894.825822,
      "httpOnly": true,
      "secure": true,
      "sameSite": "None"
    },
    {
      "name": "_gcl_au",
      "value": "1.1.1768206100.1755454895",
      "domain": ".clarkson.edu",
      "path": "/",
      "expires": 1763230895,
      "httpOnly": false,
      "secure": false,
      "sameSite": "Lax"
    },
    {
      "name": "_gid",
      "value": "GA1.2.1257683874.1755454895",
      "domain": ".clarkson.edu",
      "path": "/",
      "expires": 1755611225,
      "httpOnly": false,
      "secure": false,
      "sameSite": "Lax"
    },
    {
      "name": "BCSessionID",
      "value": "e8036c00-d824-4e26-b6f3-0458bfb5053c",
      "domain": "clarkson.edu",
      "path": "/",
      "expires": -1,
      "httpOnly": false,
      "secure": true,
      "sameSite": "Lax"
    },
    {
      "name": "_fbp",
      "value": "fb.1.1755454895678.27619980858107586",
      "domain": ".clarkson.edu",
      "path": "/",
      "expires": 1763300826,
      "httpOnly": false,
      "secure": false,
      "sameSite": "Lax"
    },
    {
      "name": "bcookie",
      "value": "\"v=2&01301c01-533f-4214-8b7a-c2b22f543cb9\"",
      "domain": ".linkedin.com",
      "path": "/",
      "expires": 1787060827.749078,
      "httpOnly": false,
      "secure": true,
      "sameSite": "None"
    },
    {
      "name": "lidc",
      "value": "\"b=OGST09:s=O:r=O:a=O:p=O:g=3219:u=1:x=1:i=1755454895:t=1755541295:v=2:sig=AQEhxrfM6_rVrBlrzuuocF63qOZkIXpU\"",
      "domain": ".linkedin.com",
      "path": "/",
      "expires": 1755541295.851699,
      "httpOnly": false,
      "secure": true,
      "sameSite": "None"
    },
    {
      "name": "monsido",
      "value": "18E1755454897163",
      "domain": "clarkson.edu",
      "path": "/",
      "expires": 1758116828,
      "httpOnly": false,
      "secure": false,
      "sameSite": "Lax"
    },
    {
      "name": "_scid",
      "value": "52JM8GjvgxV0cU3jmi8Lz-h3CHAuYdgQ",
      "domain": ".clarkson.edu",
      "path": "/",
      "expires": 1789641596,
      "httpOnly": false,
      "secure": false,
      "sameSite": "Lax"
    },
    {
      "name": "_ttp",
      "value": "31QSeTXiNnHTTZQKeSFqfn827gi",
      "domain": ".tiktok.com",
      "path": "/",
      "expires": 1789220830.456856,
      "httpOnly": false,
      "secure": true,
      "sameSite": "None"
    },
    {
      "name": "_ScCbts",
      "value": "%5B%5D",
      "domain": ".clarkson.edu",
      "path": "/",
      "expires": 1756059699,
      "httpOnly": false,
      "secure": false,
      "sameSite": "Lax"
    },
    {
      "name": "_tt_enable_cookie",
      "value": "1",
      "domain": ".clarkson.edu",
      "path": "/",
      "expires": 1789220831,
      "httpOnly": false,
      "secure": false,
      "sameSite": "Lax"
    },
    {
      "name": "_ttp",
      "value": "01K2WM81CBN3P41MP1FYDMF9MK_.tt.1",
      "domain": ".clarkson.edu",
      "path": "/",
      "expires": 1789220831,
      "httpOnly": false,
      "secure": false,
      "sameSite": "Lax"
    },
    {
      "name": "sc_at",
      "value": "v2|H4sIAAAAAAAAAE3KwQ3AIAwDwIkiJWCruNsU1UzB8OXZ3z1uzFXKYrhbAeuJ6c5gvaQpDbRdyLsuEsS5+8f8AEV0mKFAAAAA",
      "domain": ".snapchat.com",
      "path": "/",
      "expires": 1789150901.845499,
      "httpOnly": false,
      "secure": true,
      "sameSite": "None"
    },
    {
      "name": "TapAd_TS",
      "value": "1755454901699",
      "domain": ".tapad.com",
      "path": "/",
      "expires": 1760638901.755206,
      "httpOnly": false,
      "secure": true,
      "sameSite": "None"
    },
    {
      "name": "TapAd_DID",
      "value": "02411c52-1130-47bc-9f08-aa697f4728b7",
      "domain": ".tapad.com",
      "path": "/",
      "expires": 1760638901.755262,
      "httpOnly": false,
      "secure": true,
      "sameSite": "None"
    },
    {
      "name": "TapAd_3WAY_SYNCS",
      "value": "",
      "domain": ".tapad.com",
      "path": "/",
      "expires": 1760638901.755278,
      "httpOnly": false,
      "secure": true,
      "sameSite": "None"
    },
    {
      "name": "_sctr",
      "value": "1%7C1755388800000",
      "domain": ".clarkson.edu",
      "path": "/",
      "expires": 1789641599,
      "httpOnly": false,
      "secure": false,
      "sameSite": "Lax"
    },
    {
      "name": "ar_debug",
      "value": "1",
      "domain": "px.ads.linkedin.com",
      "path": "/",
      "expires": 1758154573.749044,
      "httpOnly": true,
      "secure": true,
      "sameSite": "None"
    },
    {
      "name": "receive-cookie-deprecation",
      "value": "1",
      "domain": ".doubleclick.net",
      "path": "/",
      "expires": 1771076831.121906,
      "httpOnly": true,
      "secure": true,
      "sameSite": "None",
      "partitionKey": "https://clarkson.edu",
      "_crHasCrossSiteAncestor": true
    },
    {
      "name": "AWSALBCORS",
      "value": "tRWMwZVOzuSFdhb9k7irX8hGpPloBoOy8I8O3bK7zLJi8x6uhxdyS2hZVZzGh8boDueRFGMM04NP/KqZeZKqka1aa5kAL4gj5vz/DXK6886jTar3iDgsmd+R6F4x",
      "domain": "clarkson.blueconic.net",
      "path": "/",
      "expires": 1756129625.105985,
      "httpOnly": false,
      "secure": true,
      "sameSite": "None"
    },
    {
      "name": "_rdt_uuid",
      "value": "1755454895217.26b3ed7d-c934-46fd-8fac-8b6b62cbbe97",
      "domain": ".clarkson.edu",
      "path": "/",
      "expires": 1763300825,
      "httpOnly": false,
      "secure": true,
      "sameSite": "Strict"
    },
    {
      "name": "_ga_HSB9JE4TP2",
      "value": "GS2.1.s1755524825$o3$g0$t1755524825$j60$l0$h0",
      "domain": ".clarkson.edu",
      "path": "/",
      "expires": 1790084825.66768,
      "httpOnly": false,
      "secure": false,
      "sameSite": "Lax"
    },
    {
      "name": "_ga",
      "value": "GA1.1.261361138.1755454895",
      "domain": ".clarkson.edu",
      "path": "/",
      "expires": 1790084983.547883,
      "httpOnly": false,
      "secure": false,
      "sameSite": "Lax"
    },
    {
      "name": "AWSALB",
      "value": "Ayw0g31v8Vt799LXqa+3jt/1lI88ikIHTYLp6y3UIcOcmty1gjkzE/b8KF1B0u7Nxu/DvRtjcE3Etp8hljhdrkyIhc7/rVujwBKSd+LfQQMTYTqB8YpSoosak0vs",
      "domain": "v285.clarkson.edu",
      "path": "/",
      "expires": 1756129628.285425,
      "httpOnly": false,
      "secure": false,
      "sameSite": "Lax"
    },
    {
      "name": "AWSALBCORS",
      "value": "Ayw0g31v8Vt799LXqa+3jt/1lI88ikIHTYLp6y3UIcOcmty1gjkzE/b8KF1B0u7Nxu/DvRtjcE3Etp8hljhdrkyIhc7/rVujwBKSd+LfQQMTYTqB8YpSoosak0vs",
      "domain": "v285.clarkson.edu",
      "path": "/",
      "expires": 1756129628.28561,
      "httpOnly": false,
      "secure": true,
      "sameSite": "None"
    },
    {
      "name": "_scid_r",
      "value": "8-JM8GjvgxV0cU3jmi8Lz-h3CHAuYdgQVRcYAQ",
      "domain": ".clarkson.edu",
      "path": "/",
      "expires": 1789711528,
      "httpOnly": false,
      "secure": false,
      "sameSite": "Lax"
    },
    {
      "name": "ttcsid",
      "value": "1755524831089::2xMwce4qheLG--6WkT4k.3.1755524831090",
      "domain": ".clarkson.edu",
      "path": "/",
      "expires": 1789220831,
      "httpOnly": false,
      "secure": false,
      "sameSite": "Lax"
    },
    {
      "name": "IDE",
      "value": "AHWqTUkfYOSw6v-lxBVQarAA0rWScGohd_k41DAH7Ev6VfuKhouMyGNk2VAiGC5PZfE",
      "domain": ".doubleclick.net",
      "path": "/",
      "expires": 1790084831.121853,
      "httpOnly": true,
      "secure": true,
      "sameSite": "None"
    },
    {
      "name": "ttcsid_CR3JK2JC77UFSKJEFL9G",
      "value": "1755524831089::w7FTx9Ktm421S2h-DlfD.3.1755524831302",
      "domain": ".clarkson.edu",
      "path": "/",
      "expires": 1789220831,
      "httpOnly": false,
      "secure": false,
      "sameSite": "Lax"
    },
    {
      "name": "_ga_MXMZC0JTE4",
      "value": "GS2.1.s1755524890$o1$g1$t1755524983$j60$l0$h0",
      "domain": ".clarkson.edu",
      "path": "/",
      "expires": 1790084983.54768,
      "httpOnly": false,
      "secure": false,
      "sameSite": "Lax"
    },
    {
      "name": "AWSALBCORS",
      "value": "/6JvKV2oqT/EcTlqfCndXEwgQYhUT+fuKb+YAmgpjBHzlSq3BXu8Gr82fUZ6H7e4cNdiqVL9YIYzSEyt+p0UNdYCeiQz29tUcwElOZl3LjEi3r3cOSCEvCw3m3W9",
      "domain": "chat-us.libanswers.com",
      "path": "/",
      "expires": 1756129783.912908,
      "httpOnly": false,
      "secure": true,
      "sameSite": "None"
    }
  ],
  "origins": [
    {
      "origin": "https://clarkson.edu",
      "localStorage": [
        {
          "name": "lastExternalReferrer",
          "value": "empty"
        },
        {
          "name": "u_sclid",
          "value": "ABbVugg935r--duR5pl-EgQqkTrOvySV52JM8GjvgxV0cU3jmi8Lz-h3CHAuYdgQ"
        },
        {
          "name": "_gcl_ls",
          "value": "{\"schema\":\"gcl\",\"version\":1,\"gcl_ctr\":{\"value\":{\"value\":0,\"creationTimeMs\":1755454894855},\"expires\":1763230894855}}"
        },
        {
          "name": "lastExternalReferrerTime",
          "value": "1755524826070"
        },
        {
          "name": "u_sclid_r",
          "value": "DJbVugg935r--duR5pl-EgQqkTrOvySVoYGLVPPiTPBo74MVdHFN45ovC8_odwhwLmHYEFUXGAE"
        },
        {
          "name": "li_adsId",
          "value": "7823b817-43b8-43cb-b21e-daab8448129e"
        },
        {
          "name": "topicsLastReferenceTime",
          "value": "1755524826083"
        }
      ]
    }
  ]
}