{
  "cookies": [
    {
      "name": "_cfuvid",
      "value": "4exxdaTVRApv2vxKI_Su3Ba7HcpCXCqH56rI2V7QE_M-1755453276337-0.0.1.1-604800000",
      "domain": ".vimeo.com",
      "path": "/",
      "expires": -1,
      "httpOnly": true,
      "secure": true,
      "sameSite": "None"
    },
    {
      "name": "_gcl_au",
      "value": "1.1.849287223.1755453277",
      "domain": ".tcu.edu",
      "path": "/",
      "expires": 1763229277,
      "httpOnly": false,
      "secure": false,
      "sameSite": "Lax"
    },
    {
      "name": "_ga",
      "value": "GA1.1.444069517.1755453277",
      "domain": ".tcu.edu",
      "path": "/",
      "expires": 1790048702.418683,
      "httpOnly": false,
      "secure": false,
      "sameSite": "Lax"
    },
    {
      "name": "_node",
      "value": "62e1f5c1bd7f2c76c2bc875abb82831e90dce9bfe858b41415dc3519a9b4c965",
      "domain": "apply.tcu.edu",
      "path": "/",
      "expires": -1,
      "httpOnly": false,
      "secure": true,
      "sameSite": "None"
    },
    {
      "name": "_hash",
      "value": "1b1f831b-66e7-4da7-b175-0f23aa0cf55f",
      "domain": "apply.tcu.edu",
      "path": "/",
      "expires": 1790013277.011468,
      "httpOnly": true,
      "secure": true,
      "sameSite": "None"
    },
    {
      "name": "_hashV",
      "value": "202508/1",
      "domain": "apply.tcu.edu",
      "path": "/",
      "expires": 1790013277.011522,
      "httpOnly": true,
      "secure": true,
      "sameSite": "None"
    },
    {
      "name": "vuid",
      "value": "pl766044221.1251755525",
      "domain": ".vimeo.com",
      "path": "/",
      "expires": 1790013277.700892,
      "httpOnly": false,
      "secure": true,
      "sameSite": "None"
    },
    {
      "name": "_fbp",
      "value": "fb.1.1755453277748.862399308501010869",
      "domain": ".tcu.edu",
      "path": "/",
      "expires": 1763264703,
      "httpOnly": false,
      "secure": false,
      "sameSite": "Lax"
    },
    {
      "name": "bcookie",
      "value": "\"v=2&be417f5e-6d23-4a5d-8598-e5a112714231\"",
      "domain": ".linkedin.com",
      "path": "/",
      "expires": 1787024703.661116,
      "httpOnly": false,
      "secure": true,
      "sameSite": "None"
    },
    {
      "name": "lidc",
      "value": "\"b=TGST09:s=T:r=T:a=T:p=T:g=3101:u=1:x=1:i=1755453277:t=1755539677:v=2:sig=AQHIgwb0MjRQ2T2h9fMeszaxEvL9QRW3\"",
      "domain": ".linkedin.com",
      "path": "/",
      "expires": 1755539677.927588,
      "httpOnly": false,
      "secure": true,
      "sameSite": "None"
    },
    {
      "name": "_ga_TCYT51BBHT",
      "value": "GS2.1.s1755453276$o1$g0$t1755453278$j58$l0$h0",
      "domain": ".tcu.edu",
      "path": "/",
      "expires": 1790013278.016876,
      "httpOnly": false,
      "secure": false,
      "sameSite": "Lax"
    },
    {
      "name": "TDID",
      "value": "f03b3f93-d3f2-4c41-a291-b88ee8e8350e",
      "domain": ".adsrvr.org",
      "path": "/",
      "expires": 1786989279.245892,
      "httpOnly": false,
      "secure": true,
      "sameSite": "None"
    },
    {
      "name": "XANDR_PANID",
      "value": "3ikFV1nfBa1XGbxvEv-3F1noC4XUrIoFWs1XjjmkeFns0jGCBdkDdu9eIi7m8wGr1RR8RFrEC98I4vnXvqqafaIUiQ_3foacwZXLsV9Pujs.",
      "domain": ".adnxs.com",
      "path": "/",
      "expires": 1763229278.951892,
      "httpOnly": false,
      "secure": true,
      "sameSite": "None",
      "partitionKey": "https://tcu.edu",
      "_crHasCrossSiteAncestor": true
    },
    {
      "name": "uuid2",
      "value": "3781017493859767311",
      "domain": ".adnxs.com",
      "path": "/",
      "expires": 1763229278.95193,
      "httpOnly": true,
      "secure": true,
      "sameSite": "None"
    },
    {
      "name": "demdex",
      "value": "56392184547644084701505261994599370063",
      "domain": ".demdex.net",
      "path": "/",
      "expires": 1771005279.169219,
      "httpOnly": false,
      "secure": true,
      "sameSite": "None"
    },
    {
      "name": "dpm",
      "value": "56392184547644084701505261994599370063",
      "domain": ".dpm.demdex.net",
      "path": "/",
      "expires": 1771005279.169255,
      "httpOnly": false,
      "secure": true,
      "sameSite": "None"
    },
    {
      "name": "TDCPM",
      "value": "CAESEgoDYWFtEgsIrK6rrqXwrj4QBRIVCgZnb29nbGUSCwjW0quupfCuPhAFEhcKCGFwcG5leHVzEgsIkJGCs6Xwrj4QBRgFIAIoBjILCOKGrtu78K4-EAU4AUIEIgIIAVoHNmYyOG53N2AB",
      "domain": ".adsrvr.org",
      "path": "/",
      "expires": 1786989279.24594,
      "httpOnly": false,
      "secure": true,
      "sameSite": "None"
    },
    {
      "name": "_exposure_session",
      "value": "480ec22ebf531745a50e8e01ec731ebc",
      "domain": ".tcu.edu",
      "path": "/",
      "expires": 1756698300.89039,
      "httpOnly": true,
      "secure": false,
      "sameSite": "Lax"
    },
    {
      "name": "_parsely_session",
      "value": "{%22sid%22:1%2C%22surl%22:%22https://stories.tcu.edu/dining-on-campus%22%2C%22sref%22:%22%22%2C%22sts%22:1755488701714%2C%22slts%22:0}",
      "domain": ".tcu.edu",
      "path": "/",
      "expires": 1755490501,
      "httpOnly": false,
      "secure": false,
      "sameSite": "Lax"
    },
    {
      "name": "_parsely_visitor",
      "value": "{%22id%22:%22pid=f7b66ee964c757127d7196932aa7c951%22%2C%22session_count%22:1%2C%22last_session_ts%22:1755488701714}",
      "domain": ".tcu.edu",
      "path": "/",
      "expires": 1789652701,
      "httpOnly": false,
      "secure": false,
      "sameSite": "Lax"
    },
    {
      "name": "timezone",
      "value": "America/New_York",
      "domain": "stories.tcu.edu",
      "path": "/",
      "expires": -1,
      "httpOnly": false,
      "secure": false,
      "sameSite": "Lax"
    },
    {
      "name": "_ga_GM95J47GSV",
      "value": "GS2.1.s1755488701$o1$g0$t1755488701$j60$l0$h2144308492",
      "domain": ".tcu.edu",
      "path": "/",
      "expires": 1790048701.796356,
      "httpOnly": false,
      "secure": false,
      "sameSite": "Lax"
    },
    {
      "name": "sa-user-id",
      "value": "s%3A0-b236bcb4-6089-4652-7744-073fc6bba38a.blKKmkHdeG%2BjqXkv5HpW5Cm2FgHJpckN7RAnF9S6VTE",
      "domain": "tags.srv.stackadapt.com",
      "path": "/",
      "expires": 1787024702.220244,
      "httpOnly": false,
      "secure": true,
      "sameSite": "None"
    },
    {
      "name": "sa-user-id",
      "value": "s%3A0-b236bcb4-6089-4652-7744-073fc6bba38a.blKKmkHdeG%2BjqXkv5HpW5Cm2FgHJpckN7RAnF9S6VTE",
      "domain": ".srv.stackadapt.com",
      "path": "/",
      "expires": 1787024702.220273,
      "httpOnly": false,
      "secure": true,
      "sameSite": "None"
    },
    {
      "name": "sa-user-id-v2",
      "value": "s%3Asja8tGCJRlJ3RAc_xrujig.TAkm%2BORAZuqSTc9I2iC0pFnDbMT%2BVDp4dTTG5wve%2FUg",
      "domain": "tags.srv.stackadapt.com",
      "path": "/",
      "expires": 1787024702.220456,
      "httpOnly": false,
      "secure": true,
      "sameSite": "None"
    },
    {
      "name": "sa-user-id-v2",
      "value": "s%3Asja8tGCJRlJ3RAc_xrujig.TAkm%2BORAZuqSTc9I2iC0pFnDbMT%2BVDp4dTTG5wve%2FUg",
      "domain": ".srv.stackadapt.com",
      "path": "/",
      "expires": 1787024702.220489,
      "httpOnly": false,
      "secure": true,
      "sameSite": "None"
    },
    {
      "name": "sa-user-id-v3",
      "value": "s%3AAQAKIJTWOAh-X2chwPFDIxLSh5RwVoIds2BATugFdKBo5Z8GENQHGAIgvsOKxQY6BE5BDgxCBBOhvCg.70Hlu%2B8ZBaIFGv%2BMMyjUnMAfstRiBujQAvQin%2BXLpzU",
      "domain": "tags.srv.stackadapt.com",
      "path": "/",
      "expires": 1787024702.220403,
      "httpOnly": false,
      "secure": true,
      "sameSite": "None"
    },
    {
      "name": "sa-user-id-v3",
      "value": "s%3AAQAKIJTWOAh-X2chwPFDIxLSh5RwVoIds2BATugFdKBo5Z8GENQHGAIgvsOKxQY6BE5BDgxCBBOhvCg.70Hlu%2B8ZBaIFGv%2BMMyjUnMAfstRiBujQAvQin%2BXLpzU",
      "domain": ".srv.stackadapt.com",
      "path": "/",
      "expires": 1787024702.220432,
      "httpOnly": false,
      "secure": true,
      "sameSite": "None"
    },
    {
      "name": "NID",
      "value": "525=bXpCD8zQEmxYlmbWElwFAw7OMNclr7hxHuZFSWr86PYaTFYtvcOoAj4HLQ-AZUVY9R_oyT4S70NrkqzaTFfGqNF5zxC7pBOq-o-DO7WuKcEyAElvXIa1sdefhzca7z1sEqSbkcY6a210bxiCfGcwkAQDGucPienUccxQuWnr5PlSII1xe7aUDYr3KoY2tYH32EIM804",
      "domain": ".google.com",
      "path": "/",
      "expires": 1771299901.249415,
      "httpOnly": true,
      "secure": true,
      "sameSite": "None"
    },
    {
      "name": "__cf_bm",
      "value": ".ImBcWAO8_KHGEdLTVcqra8W4ZX2wbpxa6OeIrj6UP0-1755488702-1.0.1.1-hgNRgtaeyzLs6gFbUXAOCpr2MvCXqNhrPxDhP0zn6LVgz.c_.9RtpTLbtaEPoinNTphGs_XNjwuY7x_Ww0tMugpQRqZCznrspb3r39EaNKE",
      "domain": ".twitter.com",
      "path": "/",
      "expires": 1755490502.289306,
      "httpOnly": true,
      "secure": true,
      "sameSite": "None"
    },
    {
      "name": "_ga_4K56CBF5WB",
      "value": "GS2.1.s1755488702$o1$g0$t1755488702$j60$l0$h0",
      "domain": ".tcu.edu",
      "path": "/",
      "expires": 1790048702.418501,
      "httpOnly": false,
      "secure": false,
      "sameSite": "Lax"
    },
    {
      "name": "sa-user-id",
      "value": "s%253A0-b236bcb4-6089-4652-7744-073fc6bba38a.blKKmkHdeG%252BjqXkv5HpW5Cm2FgHJpckN7RAnF9S6VTE",
      "domain": "stories.tcu.edu",
      "path": "/",
      "expires": 1787024702,
      "httpOnly": false,
      "secure": true,
      "sameSite": "Lax"
    },
    {
      "name": "sa-user-id-v2",
      "value": "s%253Asja8tGCJRlJ3RAc_xrujig.TAkm%252BORAZuqSTc9I2iC0pFnDbMT%252BVDp4dTTG5wve%252FUg",
      "domain": "stories.tcu.edu",
      "path": "/",
      "expires": 1787024702,
      "httpOnly": false,
      "secure": true,
      "sameSite": "Lax"
    },
    {
      "name": "sa-user-id-v3",
      "value": "s%253AAQAKIJTWOAh-X2chwPFDIxLSh5RwVoIds2BATugFdKBo5Z8GENQHGAIgvsOKxQY6BE5BDgxCBBOhvCg.70Hlu%252B8ZBaIFGv%252BMMyjUnMAfstRiBujQAvQin%252BXLpzU",
      "domain": "stories.tcu.edu",
      "path": "/",
      "expires": 1787024702,
      "httpOnly": false,
      "secure": true,
      "sameSite": "Lax"
    },
    {
      "name": "_uetvid",
      "value": "b934e3207be511f0a08ed7dc65e58b41",
      "domain": ".tcu.edu",
      "path": "/",
      "expires": 1789184703,
      "httpOnly": false,
      "secure": false,
      "sameSite": "Lax"
    },
    {
      "name": "ar_debug",
      "value": "1",
      "domain": "px.ads.linkedin.com",
      "path": "/",
      "expires": 1758118449.66109,
      "httpOnly": true,
      "secure": true,
      "sameSite": "None"
    },
    {
      "name": "receive-cookie-deprecation",
      "value": "1",
      "domain": ".doubleclick.net",
      "path": "/",
      "expires": 1771040703.717792,
      "httpOnly": true,
      "secure": true,
      "sameSite": "None",
      "partitionKey": "https://tcu.edu",
      "_crHasCrossSiteAncestor": true
    },
    {
      "name": "IDE",
      "value": "AHWqTUlyFWFol_Ub_J5rT9HSjH7lh6-LL0p56V5bC3ld5zqDjl9iTuOnymn7qgJC1ew",
      "domain": ".doubleclick.net",
      "path": "/",
      "expires": 1790048703.717442,
      "httpOnly": true,
      "secure": true,
      "sameSite": "None"
    },
    {
      "name": "_uetsid",
      "value": "b934efa07be511f0af57bdd45b78f6e0|ltyinr|2|fyk|0|2056",
      "domain": ".tcu.edu",
      "path": "/",
      "expires": 1755575103,
      "httpOnly": false,
      "secure": false,
      "sameSite": "Lax"
    },
    {
      "name": "mid",
      "value": "aKKhvwAEAAHROeZuL3kYM7uZs1PZ",
      "domain": ".instagram.com",
      "path": "/",
      "expires": 1790048703.763025,
      "httpOnly": true,
      "secure": true,
      "sameSite": "None"
    },
    {
      "name": "m",
      "value": "a987953d-7b78-4a99-ba6f-1eaa0263b1ff568f32",
      "domain": "m.stripe.com",
      "path": "/",
      "expires": 1790048709.539483,
      "httpOnly": true,
      "secure": true,
      "sameSite": "None"
    },
    {
      "name": "__stripe_mid",
      "value": "34bc36b3-b196-4149-a8b1-6490587cdf8f8fa8e7",
      "domain": ".stories.tcu.edu",
      "path": "/",
      "expires": 1787024709,
      "httpOnly": false,
      "secure": true,
      "sameSite": "Strict"
    },
    {
      "name": "__stripe_sid",
      "value": "68c42d7d-6d99-4a6f-9ba3-8b08da6e52370ee406",
      "domain": ".stories.tcu.edu",
      "path": "/",
      "expires": 1755490509,
      "httpOnly": false,
      "secure": true,
      "sameSite": "Strict"
    }
  ],
  "origins": [
    {
      "origin": "https://stories.tcu.edu",
      "localStorage": [
        {
          "name": "2422a55f-6fd0-7ef4-60e7-d34db7c45009_pp",
          "value": "{\"1077247640\":[{\"id\":\"86b9a6fa-7be4-4db5-ada5-99c3abb08814\"}],\"v\":\"9608ef68-cc29-8b19-4595-ed20d7c193af\"}"
        },
        {
          "name": "sa-user-id",
          "value": "s%3A0-b236bcb4-6089-4652-7744-073fc6bba38a.blKKmkHdeG%2BjqXkv5HpW5Cm2FgHJpckN7RAnF9S6VTE"
        },
        {
          "name": "lastExternalReferrerTime",
          "value": "1755488702010"
        },
        {
          "name": "_uetvid_exp",
          "value": "Sat, 12 Sep 2026 03:45:03 GMT"
        },
        {
          "name": "_uetsid_exp",
          "value": "Tue, 19 Aug 2025 03:45:03 GMT"
        },
        {
          "name": "topicsLastReferenceTime",
          "value": "1755488703329"
        },
        {
          "name": "_uetvid",
          "value": "b934e3207be511f0a08ed7dc65e58b41"
        },
        {
          "name": "lastExternalReferrer",
          "value": "empty"
        },
        {
          "name": "_gcl_ls",
          "value": "{\"schema\":\"gcl\",\"version\":1,\"gcl_ctr\":{\"value\":{\"value\":0,\"creationTimeMs\":1755488701834},\"expires\":1763264701834}}"
        },
        {
          "name": "_uetsid",
          "value": "b934efa07be511f0af57bdd45b78f6e0|ltyinr|2|fyk|0|2056"
        },
        {
          "name": "sa-user-id-v3",
          "value": "s%3AAQAKIJTWOAh-X2chwPFDIxLSh5RwVoIds2BATugFdKBo5Z8GENQHGAIgvsOKxQY6BE5BDgxCBBOhvCg.70Hlu%2B8ZBaIFGv%2BMMyjUnMAfstRiBujQAvQin%2BXLpzU"
        },
        {
          "name": "li_adsId",
          "value": "af46ba5f-c055-472b-8502-8deacee8104e"
        },
        {
          "name": "sa-user-id-v2",
          "value": "s%3Asja8tGCJRlJ3RAc_xrujig.TAkm%2BORAZuqSTc9I2iC0pFnDbMT%2BVDp4dTTG5wve%2FUg"
        },
        {
          "name": "2422a55f-6fd0-7ef4-60e7-d34db7c45009_st",
          "value": "1755488703626"
        }
      ]
    },
    {
      "origin": "https://www.tcu.edu",
      "localStorage": [
        {
          "name": "lastExternalReferrer",
          "value": "empty"
        },
        {
          "name": "2422a55f-6fd0-7ef4-60e7-d34db7c45009_pp",
          "value": "{\"1077247640\":[{\"id\":\"86b9a6fa-7be4-4db5-ada5-99c3abb08814\"}],\"v\":\"9608ef68-cc29-8b19-4595-ed20d7c193af\"}"
        },
        {
          "name": "_gcl_ls",
          "value": "{\"schema\":\"gcl\",\"version\":1,\"gcl_ctr\":{\"value\":{\"value\":0,\"creationTimeMs\":1755453276564},\"expires\":1763229276564}}"
        },
        {
          "name": "lastExternalReferrerTime",
          "value": "1755453277745"
        },
        {
          "name": "2422a55f-6fd0-7ef4-60e7-d34db7c45009_st",
          "value": "1755453277497"
        },
        {
          "name": "li_adsId",
          "value": "e4e754d3-1714-4b81-bae6-06bd73820f0a"
        },
        {
          "name": "topicsLastReferenceTime",
          "value": "1755453277755"
        }
      ]
    }
  ]
}